MANIFEST.in
README
README.rst
setup.cfg
setup.py
pydstat/__init__.py
pydstat/cmd.py
pydstat/pydstat.py
pydstat.egg-info/PKG-INFO
pydstat.egg-info/SOURCES.txt
pydstat.egg-info/dependency_links.txt
pydstat.egg-info/entry_points.txt
pydstat.egg-info/top_level.txt