Metadata-Version: 1.0
Name: pydstat
Version: 1.0.1
Summary: A Pythonic Wrapper for pidstat.
Home-page: https://github.com/ampledata/pydstat
Author: Greg Albrecht
Author-email: gba@splunk.com
License: Apache License 2.0
Platform: UNKNOWN
